README.md
setup.cfg
setup.py
libnsga2/__init__.py
libnsga2/evolution.py
libnsga2/individual.py
libnsga2/population.py
libnsga2/problem.py
libnsga2/utils.py
libnsga2.egg-info/PKG-INFO
libnsga2.egg-info/SOURCES.txt
libnsga2.egg-info/dependency_links.txt
libnsga2.egg-info/top_level.txt