Metadata-Version: 1.0
Name: libnsga2
Version: 0.1.1
Summary: A NSGA-II implementation
Home-page: https://github.com/amrondonp/NSGA-II
Author: Andres Rondon
Author-email: amrondonp@gmail.com
License: MIT
Keywords: nsga2 nsga ga multi-objective
Platform: UNKNOWN
